{"name":"IntegriDB: Verifiable SQL for Outsourced Databases","tagline":"","body":"22st ACM Conference on Computer and Communications Security 2015  \r\n[Link to paper](http://integridb.github.io/IntegriDB.pdf)  \r\n[Link to slides](https://github.com/integridb/talk.pptx)  \r\n[Link to code](https://github.com/integridb/Code)\r\n\r\n### Authors\r\n[Yupeng Zhang](http://www.umiacs.umd.edu/~zhangyp/) (University of Maryland, College Park)  \r\n[Jonathan Katz](http://www.cs.umd.edu/~jkatz/) (University of Maryland, College Park)   \r\n[Charalampos Papamanthou](http://www.ece.umd.edu/~cpap/) (University of Maryland, College Park)\r\n\r\n### Contact\r\nYupeng Zhang (zhangyp@umd.edu)\r\n","google":"","note":"Don't delete this file! It's used internally to help with page regeneration."}